onegov.org-1.6.1-py3.6-nspkg.pth
onegov/org/.gitignore
onegov/org/__init__.py
onegov/org/app.py
onegov/org/cli.py
onegov/org/converters.py
onegov/org/cronjobs.py
onegov/org/custom.py
onegov/org/directives.py
onegov/org/elements.py
onegov/org/initial_content.py
onegov/org/layout.py
onegov/org/mail.py
onegov/org/path.py
onegov/org/redirects.py
onegov/org/request.py
onegov/org/security.py
onegov/org/translations.py
onegov/org/upgrade.py
onegov/org/utils.py
onegov/org/assets/css/fullcalendar.css
onegov/org/assets/css/jquery.datetimepicker.css
onegov/org/assets/css/photoswipe-skin.css
onegov/org/assets/css/photoswipe.css
onegov/org/assets/css/redactor.css
onegov/org/assets/js/ace-mode-form.js
onegov/org/assets/js/ace-mode-markdown.js
onegov/org/assets/js/ace-mode-xml.js
onegov/org/assets/js/ace-mode-yaml.js
onegov/org/assets/js/ace-theme-tomorrow.js
onegov/org/assets/js/ace.js
onegov/org/assets/js/asmcrypto-lite.js
onegov/org/assets/js/bufferbuttons.js
onegov/org/assets/js/code_editor.js
onegov/org/assets/js/common.js
onegov/org/assets/js/confirm.jsx
onegov/org/assets/js/date-range-selector.js
onegov/org/assets/js/datetimepicker.js
onegov/org/assets/js/daypicker.js
onegov/org/assets/js/definedlinks.js
onegov/org/assets/js/editalttext.js
onegov/org/assets/js/editor.js
onegov/org/assets/js/filedigest.js
onegov/org/assets/js/filemanager.js
onegov/org/assets/js/foundation.alert.js
onegov/org/assets/js/foundation.dropdown.js
onegov/org/assets/js/foundation.js
onegov/org/assets/js/foundation.orbit.js
onegov/org/assets/js/foundation.reveal.js
onegov/org/assets/js/foundation.topbar.js
onegov/org/assets/js/fullcalendar.de.js
onegov/org/assets/js/fullcalendar.fr.js
onegov/org/assets/js/fullcalendar.js
onegov/org/assets/js/global.js
onegov/org/assets/js/imagemanager.js
onegov/org/assets/js/input_with_button.js
onegov/org/assets/js/intercooler.js
onegov/org/assets/js/jquery.cookie.js
onegov/org/assets/js/jquery.datetimepicker.js
onegov/org/assets/js/jquery.js
onegov.org-1.6.1.dist-info/METADATA
onegov.org-1.6.1.dist-info/WHEEL
onegov.org-1.6.1.dist-info/entry_points.txt
onegov.org-1.6.1.dist-info/namespace_packages.txt
onegov.org-1.6.1.dist-info/top_level.txt
onegov.org-1.6.1.dist-info/RECORD
