Metadata-Version: 2.1
Name: onegov.org
Version: 1.6.1
Summary: A OneGov Cloud base application for organisations.
Home-page: http://github.com/OneGov/onegov.org
Author: Seantis GmbH
Author-email: info@seantis.ch
License: GPLv2
Platform: any
Classifier: Intended Audience :: Developers
Classifier: Programming Language :: Python :: 3 :: Only
Classifier: Programming Language :: Python :: 3.6
Classifier: Programming Language :: Python :: 3.7
Classifier: Topic :: Software Development :: Libraries :: Python Modules
Classifier: License :: OSI Approved :: GNU General Public License v2 (GPLv2)
Requires-Python: >=3.6
Requires-Dist: babel
Requires-Dist: click
Requires-Dist: icalendar
Requires-Dist: isodate
Requires-Dist: lxml
Requires-Dist: onegov.chat
Requires-Dist: onegov.core (>=0.79.1)
Requires-Dist: onegov.directory (>=0.4.1)
Requires-Dist: onegov.event (>=1.1.0)
Requires-Dist: onegov.file (>=0.2.1)
Requires-Dist: onegov.form (>=0.18.0)
Requires-Dist: onegov.foundation (>=0.0.7)
Requires-Dist: onegov.gis
Requires-Dist: onegov.newsletter (>=0.1.0)
Requires-Dist: onegov.page (>=0.1.0)
Requires-Dist: onegov.pay
Requires-Dist: onegov.people (>=0.9.1)
Requires-Dist: onegov.recipient
Requires-Dist: onegov.reservation (>=0.3.0)
Requires-Dist: onegov.search (>=1.0.0)
Requires-Dist: onegov.shared
Requires-Dist: onegov.ticket (>=0.4.1)
Requires-Dist: onegov.user (>=0.11.0)
Requires-Dist: Pillow (!=5.4.0)
Requires-Dist: purl
Requires-Dist: python-dateutil
Requires-Dist: python-magic (>=0.4.12)
Requires-Dist: pytz
Requires-Dist: PyYAML
Requires-Dist: rjsmin
Requires-Dist: sedate
Requires-Dist: translationstring
Requires-Dist: tqdm
Requires-Dist: webtest
Provides-Extra: test
Requires-Dist: coverage ; extra == 'test'
Requires-Dist: freezegun ; extra == 'test'
Requires-Dist: onegov-testing ; extra == 'test'
Requires-Dist: pyquery ; extra == 'test'
Requires-Dist: pytest-localserver ; extra == 'test'
Requires-Dist: requests-mock ; extra == 'test'
Requires-Dist: vcrpy ; extra == 'test'
